email_confirm_la/__init__.py
email_confirm_la/admin.py
email_confirm_la/apps.py
email_confirm_la/compat.py
email_confirm_la/conf.py
email_confirm_la/exceptions.py
email_confirm_la/models.py
email_confirm_la/signals.py
email_confirm_la/urls.py
email_confirm_la/utils.py
email_confirm_la/validators.py
email_confirm_la/views.py
email_confirm_la/management/__init__.py
email_confirm_la/management/commands/__init__.py
email_confirm_la/management/commands/clear_expired_email_confirmations.py
email_confirm_la/migrations/0001_initial.py
email_confirm_la/migrations/0002_auto_20170713_1447.py
email_confirm_la/migrations/__init__.py
email_confirm_la/templates/email_confirm_la/email_confirmation_expiration.html
email_confirm_la/templates/email_confirm_la/email_confirmation_fail.html
email_confirm_la/templates/email_confirm_la/email_confirmation_success.html
email_confirm_la/templates/email_confirm_la/email/email_confirmation_message.html
email_confirm_la/templates/email_confirm_la/email/email_confirmation_subject.txt
email_confirm_la/tests/__init__.py
email_confirm_la/tests/base.py
email_confirm_la/tests/test_admin.py
email_confirm_la/tests/test_models.py
email_confirm_la/tests/test_views.py
django_email_confirm_la-3.0.0.dist-info/LICENSE
django_email_confirm_la-3.0.0.dist-info/METADATA
django_email_confirm_la-3.0.0.dist-info/WHEEL
django_email_confirm_la-3.0.0.dist-info/top_level.txt
django_email_confirm_la-3.0.0.dist-info/RECORD
