Metadata-Version: 2.1
Name: django-email-confirm-la
Version: 3.0.0
Summary: Django email confirmation for any Model and any Field.
Home-page: https://github.com/vinta/django-email-confirm-la
Author: Vinta Chen
Author-email: vinta.chen@gmail.com
License: The MIT License (MIT)
Requires-Dist: django (<3.2,>1.11)
